xiaogui/__init__.py
xiaogui/hello.py
xiaogui-0.0.2.dist-info/LICENSE
xiaogui-0.0.2.dist-info/METADATA
xiaogui-0.0.2.dist-info/WHEEL
xiaogui-0.0.2.dist-info/top_level.txt
xiaogui-0.0.2.dist-info/RECORD
