Metadata-Version: 2.1
Name: xiaogui
Version: 0.0.2
Summary: A package for xiaogui robot
Home-page: https://github.com/xiaogui-robot/xiaogui-python.git
Author: xiaogui robot
Author-email: webmaster@jibu-tech.com
License: UNKNOWN
Project-URL: Bug Tracker, https://github.com/xiaogui-robot/xiaogui-python/issues
Platform: UNKNOWN
Classifier: Programming Language :: Python :: 3
Classifier: License :: OSI Approved :: MIT License
Classifier: Operating System :: OS Independent
Requires-Python: >=3.6
License-File: LICENSE
